setup.cfg
setup.py
wikidoc/__init__.py
wikidoc/_version.py
wikidoc/build_docs.py
wikidoc/exceptions.py
wikidoc/main.py
wikidoc.egg-info/PKG-INFO
wikidoc.egg-info/SOURCES.txt
wikidoc.egg-info/dependency_links.txt
wikidoc.egg-info/entry_points.txt
wikidoc.egg-info/requires.txt
wikidoc.egg-info/top_level.txt