Metadata-Version: 1.0
Name: wikidoc
Version: 0.2.1
Summary: Generate a static site from a Github wiki
Home-page: https://github.com/serra/wiki-to-doc
Author: Marijn van der Zee
Author-email: marijn@serraict.com
License: Apache 2.0
Keywords: github wiki static site html
Platform: UNKNOWN
